<?xml version="1.0" encoding="UTF-8"?>
<flow id="169ea3ad-3558-4166-8dfc-5653f0be2f1c">
  <descriptionCdata><![CDATA[169ea3ad-3558-4166-8dfc-5653f0be2f1c.3dc546ff-9723-44bf-b85a-5f3a0ecec7ab.description=<pre>This operation writes the data from "contents" input to the requested file. The operation can be used to overwrite existing content of the file, append extra lines to it or even create a new file.\n\nInputs\:\n    source -  Full path to file. If the file does not exist it is created first.\n    contents - The content that should be written to the file. This input field can contain more lines, separated by a delimiter. If it contains the new line character (\\n or \\r\\n), but this is not the delimiter, this character will be escaped and written to file.  \nExample\: "This is line no. 01\\nThis is line no. 2\\n" where \\n is the delimiter.\n    delimiter - Specifies the newline delimiter that is used to split the "contents" input field into separate lines that will be further written to the given file.\nExamples\: \\n, \\r\\n, etc\n    characterSet - The character encoding used to write to the file. \nDefault\: UTF-8. \nValid values\: windows-1252, UTF-16, UTF-16BE,  ISO-8859-1, US-ASCII, Shift_JIS etc.\n    overwrite - Specifies whether to overwrite the file or append to it. \nDefault\: true. \nValid values\: true, false or the empty string. If this is left empty, the file will be overwritten.\n\nResults\:\n    returnResult - This is the primary output. It contains the "success" confirmation message if the operation successfully completes, or an exception message otherwise.\n    returnCode - It has the value 0 if the operation successfully completes and 1 otherwise.\n    exception - This contains an exception message if the operation fails.\n\nResponses\:\n    success - File/directory was written successfully.\n    failure - Unable to write to file/directory, empty contents or source.\n\nExamples\:\n1. This is a valid input example for using this operation on Windows\:\n    source\: C\:\\Program Files\\example.txt\n    contents\: line1,line2,line3\n    delimiter\: ,\n\n2. This is a valid input example for using this operation on Linux\:\n    source\: /root/example.txt\n    contents\: line1,line2,line3\n    delimiter\: ,\n</pre>
169ea3ad-3558-4166-8dfc-5653f0be2f1c.6039fad4-4f9d-4fbd-a167-de2e2c3bdb13.description=<pre>Uses Secure FTP (SFTP) to send a file on a RAS to a remote host.  \n\nInputs\:\nhost - IP address/host name.\nport - The port to connect to on host.\nusername - Remote username.\npassword - Password to authenticate. If using a private key file this will be used as the passphrase for the file.\nprivateKey - Absolute path for private key file for public/private key authentication.\nlocalFile - The path to the file on the RAS to be copied remotely using SFTP.\nremoteLocation - The remote location where the file is to be placed.\ncharacterSet - The name of the control encoding to use. Examples\: UTF-8, EUC-JP, SJIS.  Default is UTF-8.\ncloseSession - Close the SSH session at completion of operation?  Default value is true.  If false the SSH session can be reused by other SFTP commands in the same flow.  Valid values\: true, false.\n\nResponses\:\nsuccess - Command completed successfully.\nfailure - Command failed.\n\nResult\:\nLocal file will be copied to Remote system.\n</pre>
169ea3ad-3558-4166-8dfc-5653f0be2f1c.80db9661-3fbc-46b4-b6a8-b6e5c80b5d63.prompt=Colocar fecha en formato dd/mm/aaaa en caso de reproceso 
169ea3ad-3558-4166-8dfc-5653f0be2f1c.bc5912fd-3e0e-4a2b-8180-6fd95e351cdc.callout=Obtener 325 y FUENTE 49 para hacer la consicliacion. 
]]></descriptionCdata>
  <annotation></annotation>
  <name>Conciliacion POS EMISOR VISA - BancoAzteca Guatemala Banco Hipotecario El Salvador</name>
  <categories/>
  <inputs>
    <staticBinding id="6280ce0f-dd65-41a1-a500-c9cd1e0b26c6">
      <annotation></annotation>
      <assignFromContext>true</assignFromContext>
      <assignToContext>false</assignToContext>
      <inputType>STRING</inputType>
      <isList>false</isList>
      <required>false</required>
      <isPersisted>true</isPersisted>
      <inputSymbol>Entidad</inputSymbol>
      <listDelimiter>,</listDelimiter>
      <value>1301</value>
      <record>false</record>
    </staticBinding>
    <staticBinding id="044d05d7-cd85-43a8-bc7a-389f65c201f9">
      <annotation></annotation>
      <assignFromContext>true</assignFromContext>
      <assignToContext>false</assignToContext>
      <inputType>STRING</inputType>
      <isList>false</isList>
      <required>false</required>
      <isPersisted>true</isPersisted>
      <inputSymbol>ArchivoPostBanco</inputSymbol>
      <listDelimiter>,</listDelimiter>
      <value>I1351.B1301TX325</value>
      <record>false</record>
    </staticBinding>
    <userInputBinding id="80db9661-3fbc-46b4-b6a8-b6e5c80b5d63">
      <annotation></annotation>
      <assignFromContext>true</assignFromContext>
      <assignToContext>false</assignToContext>
      <inputType>STRING</inputType>
      <isList>false</isList>
      <required>false</required>
      <isPersisted>true</isPersisted>
      <inputSymbol>FechaEntrada</inputSymbol>
      <listDelimiter>,</listDelimiter>
      <record>false</record>
      <prompt>169ea3ad-3558-4166-8dfc-5653f0be2f1c.80db9661-3fbc-46b4-b6a8-b6e5c80b5d63.prompt</prompt>
      <isMultiSelect>false</isMultiSelect>
      <sourceDelimiter>|</sourceDelimiter>
    </userInputBinding>
    <staticBinding id="8acddf1d-06ba-40d0-9383-a98d4e0ca3d2">
      <annotation></annotation>
      <assignFromContext>true</assignFromContext>
      <assignToContext>false</assignToContext>
      <inputType>STRING</inputType>
      <isList>false</isList>
      <required>false</required>
      <isPersisted>true</isPersisted>
      <inputSymbol>Buzon Banco</inputSymbol>
      <listDelimiter>,</listDelimiter>
      <value>MB000061</value>
      <record>false</record>
    </staticBinding>
    <staticBinding id="0db9b789-2d32-4beb-9500-7b607d74b7ad">
      <annotation></annotation>
      <assignFromContext>true</assignFromContext>
      <assignToContext>false</assignToContext>
      <inputType>STRING</inputType>
      <isList>false</isList>
      <required>false</required>
      <isPersisted>true</isPersisted>
      <inputSymbol>BIN</inputSymbol>
      <listDelimiter>,</listDelimiter>
      <value>&apos;415426\|422156\|483111&apos;</value>
      <record>false</record>
    </staticBinding>
    <staticBinding id="d37479dd-f4a7-4b59-95cf-c8112a81d414">
      <annotation></annotation>
      <assignFromContext>true</assignFromContext>
      <assignToContext>true</assignToContext>
      <inputType>STRING</inputType>
      <isList>false</isList>
      <required>false</required>
      <isPersisted>true</isPersisted>
      <inputSymbol>FIID1</inputSymbol>
      <listDelimiter>,</listDelimiter>
      <value>PA01</value>
      <record>false</record>
    </staticBinding>
    <staticBinding id="ca05f61d-afc8-4ffa-900e-d0219bc71aa2">
      <annotation></annotation>
      <assignFromContext>true</assignFromContext>
      <assignToContext>false</assignToContext>
      <inputType>STRING</inputType>
      <isList>false</isList>
      <required>false</required>
      <isPersisted>true</isPersisted>
      <inputSymbol>NomBanco</inputSymbol>
      <listDelimiter>,</listDelimiter>
      <value>Azteca Panama</value>
      <record>false</record>
    </staticBinding>
  </inputs>
  <possibleResponses>
    <opResponse id="373a821c-1106-4714-8b1c-3aa5897baa9e">
      <annotation></annotation>
      <name>success</name>
      <isDefault>true</isDefault>
      <onFailure>false</onFailure>
      <type>RESOLVED</type>
      <matchRules/>
    </opResponse>
  </possibleResponses>
  <availableResultExpressions/>
  <resultExpression id="80dfb7f9-4299-47cb-85d8-7324ee6b1201">
    <annotation></annotation>
    <name>FailureMessage</name>
    <fieldName>FailureMessage</fieldName>
    <sourceType>RAWRESULT</sourceType>
    <filters/>
  </resultExpression>
  <iconSpec id="69647a3e-f228-41a1-8346-32050ed2c928">
    <baseIcon>flow.png</baseIcon>
    <basePath>System</basePath>
    <readOnly>false</readOnly>
    <layers/>
  </iconSpec>
  <callouts>
    <callout id="bc5912fd-3e0e-4a2b-8180-6fd95e351cdc">
      <text>169ea3ad-3558-4166-8dfc-5653f0be2f1c.bc5912fd-3e0e-4a2b-8180-6fd95e351cdc.callout</text>
      <bounds>
        <x>122.0</x>
        <y>11.0</y>
        <width>193.0</width>
        <height>42.0</height>
      </bounds>
      <layer>-1</layer>
      <step>
        <refId>400eb22b-2739-45a1-a8ff-3c7722f41ceb</refId>
      </step>
    </callout>
  </callouts>
  <checkPointFlow>true</checkPointFlow>
  <compatibleRuntimeContext>false</compatibleRuntimeContext>
  <historyCheckPointFlow>true</historyCheckPointFlow>
  <steps>
    <step id="597b944e-813f-4868-9355-22499d5cc024">
      <annotation></annotation>
      <name>Determinar Fechas</name>
      <bounds>
        <x>0.0</x>
        <y>6.0</y>
      </bounds>
      <layer>-1</layer>
      <hideInbound>false</hideInbound>
      <iconSpec id="6a26bd01-c084-4980-9852-5fbccebedb69">
        <baseIcon>flow.png</baseIcon>
        <basePath>System</basePath>
        <readOnly>false</readOnly>
        <layers/>
      </iconSpec>
      <addResultToRunContext>false</addResultToRunContext>
      <isCriticalStep>false</isCriticalStep>
      <isNonBlocking>false</isNonBlocking>
      <isParallelStep>false</isParallelStep>
      <isSingleResponse>false</isSingleResponse>
      <recordInHistory>false</recordInHistory>
      <recordRawOutput>true</recordRawOutput>
      <recordPrimaryOutput>true</recordPrimaryOutput>
      <checkPointStep>true</checkPointStep>
      <historyCheckPointStep>true</historyCheckPointStep>
      <scriptResultStep>false</scriptResultStep>
      <userPrompt></userPrompt>
      <bindings>
        <staticBinding id="ac282a34-c40e-4b6f-b42a-3c30820b45bc">
          <annotation></annotation>
          <assignFromContext>true</assignFromContext>
          <assignToContext>false</assignToContext>
          <inputType>STRING</inputType>
          <isList>false</isList>
          <required>false</required>
          <isPersisted>true</isPersisted>
          <inputSymbol>FechaEntrada</inputSymbol>
          <listDelimiter>,</listDelimiter>
          <value></value>
          <record>false</record>
        </staticBinding>
      </bindings>
      <transitions>
        <transition id="96811d6e-bc21-4b13-babd-b0f819f7ec53">
          <annotation></annotation>
          <name>Un Dia</name>
          <command>NEXT</command>
          <linkMode>false</linkMode>
          <responseSymbol>Un Dia</responseSymbol>
          <shouldHandoff>false</shouldHandoff>
          <transitionValue>0.0</transitionValue>
          <destination>
            <refId>400eb22b-2739-45a1-a8ff-3c7722f41ceb</refId>
          </destination>
          <source>
            <refId>597b944e-813f-4868-9355-22499d5cc024</refId>
          </source>
          <positions>
            <point>
              <x>127.0</x>
              <y>54.0</y>
            </point>
            <point>
              <x>146.0</x>
              <y>209.0</y>
            </point>
          </positions>
          <labelPosition>
            <x>333.0</x>
            <y>0.0</y>
          </labelPosition>
        </transition>
        <transition id="7a3d63a7-bdc6-44a2-adbf-cab2834a1a23">
          <annotation></annotation>
          <name>Dos Dias</name>
          <command>NEXT</command>
          <linkMode>false</linkMode>
          <responseSymbol>Dos Dias</responseSymbol>
          <shouldHandoff>false</shouldHandoff>
          <transitionValue>0.0</transitionValue>
          <destination>
            <refId>400eb22b-2739-45a1-a8ff-3c7722f41ceb</refId>
          </destination>
          <source>
            <refId>597b944e-813f-4868-9355-22499d5cc024</refId>
          </source>
          <positions>
            <point>
              <x>22.32258064516129</x>
              <y>72.0</y>
            </point>
            <point>
              <x>107.0</x>
              <y>97.0</y>
            </point>
            <point>
              <x>100.0</x>
              <y>147.0</y>
            </point>
            <point>
              <x>50.0</x>
              <y>227.0</y>
            </point>
          </positions>
          <labelPosition>
            <x>333.0</x>
            <y>0.0</y>
          </labelPosition>
        </transition>
      </transitions>
      <properties/>
      <opRef>
        <refId>bd3afb5d-58f6-40d0-9d77-0b136c8d3f16</refId>
      </opRef>
      <assignments>
        <flowVariableAssignment id="3b8672ef-167b-4d40-88ae-22a7239a34d3">
          <annotation></annotation>
          <name>assignment</name>
          <action>OVERWRITE</action>
          <assignmentTargetType>FLOW_VARIABLE</assignmentTargetType>
          <contextKey>FechaAC</contextKey>
          <expression id="d2849458-f6fd-412d-adf9-c2e8dcc701e8">
            <annotation></annotation>
            <name>Result Field: FechaAC</name>
            <fieldName>FechaAC</fieldName>
            <sourceType>RAWRESULT</sourceType>
            <filters/>
          </expression>
        </flowVariableAssignment>
        <flowVariableAssignment id="2035259f-9227-4998-acf9-0d481c4f18cb">
          <annotation></annotation>
          <name>assignment</name>
          <action>OVERWRITE</action>
          <assignmentTargetType>FLOW_VARIABLE</assignmentTargetType>
          <contextKey>FechaAC01</contextKey>
          <expression id="decaf927-2a44-4656-82c3-9ae49fbdb337">
            <annotation></annotation>
            <name>Result: hoy</name>
            <fieldName>hoy</fieldName>
            <sourceType>AVAILABLE_RESULT</sourceType>
            <filters/>
          </expression>
        </flowVariableAssignment>
        <flowVariableAssignment id="cb48373d-517b-4bf0-ac69-13fd50ffd026">
          <annotation></annotation>
          <name>assignment</name>
          <action>OVERWRITE</action>
          <assignmentTargetType>FLOW_VARIABLE</assignmentTargetType>
          <contextKey>hoy</contextKey>
          <expression id="79768937-7179-4321-81b8-1a6d712f14b5">
            <annotation></annotation>
            <name>Result: hoy</name>
            <fieldName>hoy</fieldName>
            <sourceType>AVAILABLE_RESULT</sourceType>
            <filters/>
          </expression>
        </flowVariableAssignment>
        <flowVariableAssignment id="386ed0d3-445e-4d24-83b6-8c78ed071b9e">
          <annotation></annotation>
          <name>assignment</name>
          <action>OVERWRITE</action>
          <assignmentTargetType>FLOW_VARIABLE</assignmentTargetType>
          <contextKey>ayer</contextKey>
          <expression id="cbb1d2e6-34fd-495b-96aa-7cc96ab54984">
            <annotation></annotation>
            <name>Result: ayer</name>
            <fieldName>ayer</fieldName>
            <sourceType>AVAILABLE_RESULT</sourceType>
            <filters/>
          </expression>
        </flowVariableAssignment>
        <flowVariableAssignment id="90f93998-e9c2-467f-b662-bc0af7b70874">
          <annotation></annotation>
          <name>assignment</name>
          <action>OVERWRITE</action>
          <assignmentTargetType>FLOW_VARIABLE</assignmentTargetType>
          <contextKey>antesAyer</contextKey>
          <expression id="578f09ab-adbd-469a-90cb-603748e9cb5b">
            <annotation></annotation>
            <name>Result: antesAyer</name>
            <fieldName>antesAyer</fieldName>
            <sourceType>AVAILABLE_RESULT</sourceType>
            <filters/>
          </expression>
        </flowVariableAssignment>
      </assignments>
      <throttleSize>0</throttleSize>
    </step>
    <step id="df326220-390d-4717-807b-ed5e825c49dd">
      <annotation></annotation>
      <name>ReadFile SubFlujo [POSRE]</name>
      <bounds>
        <x>0.0</x>
        <y>331.0</y>
      </bounds>
      <layer>-1</layer>
      <hideInbound>false</hideInbound>
      <iconSpec id="8b858ed9-67d2-43c1-b265-fcb52c28f535">
        <baseIcon>flow.png</baseIcon>
        <basePath>System</basePath>
        <readOnly>false</readOnly>
        <layers/>
      </iconSpec>
      <addResultToRunContext>false</addResultToRunContext>
      <isCriticalStep>false</isCriticalStep>
      <isNonBlocking>false</isNonBlocking>
      <isParallelStep>false</isParallelStep>
      <isSingleResponse>false</isSingleResponse>
      <recordInHistory>false</recordInHistory>
      <recordRawOutput>true</recordRawOutput>
      <recordPrimaryOutput>true</recordPrimaryOutput>
      <checkPointStep>true</checkPointStep>
      <historyCheckPointStep>true</historyCheckPointStep>
      <scriptResultStep>false</scriptResultStep>
      <userPrompt></userPrompt>
      <bindings>
        <staticBinding id="19a1c8ff-6b2f-4dbd-8e5e-ad18d425f785">
          <annotation></annotation>
          <fromContextKey>ArchivoPOSRE</fromContextKey>
          <assignFromContext>true</assignFromContext>
          <assignToContext>false</assignToContext>
          <inputType>STRING</inputType>
          <isList>false</isList>
          <required>false</required>
          <isPersisted>true</isPersisted>
          <inputSymbol>File</inputSymbol>
          <listDelimiter>,</listDelimiter>
          <value></value>
          <record>false</record>
        </staticBinding>
        <staticBinding id="a00c3d88-c726-4383-be82-f205adfaaf85">
          <annotation></annotation>
          <fromContextKey>Entidad</fromContextKey>
          <assignFromContext>true</assignFromContext>
          <assignToContext>false</assignToContext>
          <inputType>STRING</inputType>
          <isList>false</isList>
          <required>false</required>
          <isPersisted>true</isPersisted>
          <inputSymbol>Filter</inputSymbol>
          <listDelimiter>,</listDelimiter>
          <value>10170925H021</value>
          <record>false</record>
        </staticBinding>
      </bindings>
      <transitions>
        <transition id="57627b66-b84c-4ca0-920b-4d7122734c0e">
          <annotation></annotation>
          <name>success</name>
          <command>NEXT</command>
          <linkMode>false</linkMode>
          <responseSymbol>success</responseSymbol>
          <shouldHandoff>false</shouldHandoff>
          <transitionValue>0.0</transitionValue>
          <destination>
            <refId>4fedc28d-e325-405a-b332-b0d06f8f8831</refId>
          </destination>
          <source>
            <refId>df326220-390d-4717-807b-ed5e825c49dd</refId>
          </source>
          <positions>
            <point>
              <x>139.0</x>
              <y>376.0</y>
            </point>
            <point>
              <x>337.0</x>
              <y>321.0</y>
            </point>
          </positions>
          <labelPosition>
            <x>333.0</x>
            <y>0.0</y>
          </labelPosition>
        </transition>
      </transitions>
      <properties/>
      <opRef>
        <refId>4bc1a997-f980-48e6-9979-37d5d93429f0</refId>
      </opRef>
      <assignments>
        <flowVariableAssignment id="4298bef1-84fb-4fca-867b-7c021b6064a3">
          <annotation></annotation>
          <name>assignment</name>
          <action>OVERWRITE</action>
          <assignmentTargetType>FLOW_VARIABLE</assignmentTargetType>
          <contextKey>Lectura Archivo TX325 VISA</contextKey>
          <expression id="5d55756d-01d6-419e-a66d-710e099c7298">
            <annotation></annotation>
            <name>Result: Leido</name>
            <fieldName>Leido</fieldName>
            <sourceType>AVAILABLE_RESULT</sourceType>
            <filters>
              <stripWhitespaceFilter id="46c2c532-fae4-4e43-bfbb-f2d58dccd4fd">
                <annotation></annotation>
                <name>Strip Whitespace</name>
              </stripWhitespaceFilter>
              <scriptletFilter id="dac1b416-e469-4704-b1f1-6bfb559bb556">
                <annotation></annotation>
                <name>Scriptlet</name>
                <scriptlet id="0ef31542-cf03-4f5e-9856-7f889a32205a">
                  <annotation></annotation>
                  <name>default</name>
                  <script>if (scriptletInput !== null) {
  var ent=scriptletInput.split(&quot;\n&quot;);
  var salida=&quot;&quot;;
  
  for(i=0;i&lt;ent.length;i++){
  	salida+=ent[i].substring(0,5)+&quot;,&quot;+ent[i].substring(5,10)+&quot;,&quot;+ent[i].substring(10,26)+&quot;,&quot;;
  	salida+=ent[i].substring(26,42).replace(/^\s+/,&quot;&quot;).replace(/\s+$/,&quot;&quot;)+&quot;,&quot;+ent[i].substring(42,44)+&quot;,&quot;;
  	salida+=ent[i].substring(44,57)+&quot;,&quot;+ent[i].substring(57,70)+&quot;,&quot;+ent[i].substring(70,83)+&quot;,&quot;+ent[i].substring(83,130).replace(/^\s+/,&quot;&quot;).replace(/\s+$/,&quot;&quot;)+&quot;,&quot;;
  	salida+=ent[i].substring(130,150).replace(/^\s+/,&quot;&quot;).replace(/\s+$/,&quot;&quot;)+&quot;,&quot;+ent[i].substring(150,181)+&quot;,&quot;+ent[i].substring(181,205).replace(/^\s+/,&quot;&quot;).replace(/\s+$/,&quot;&quot;)+&quot;,&quot;;
  	salida+=ent[i].substring(205,207)+&quot;,&quot;+ent[i].substring(207,308).replace(/^\s+/,&quot;&quot;).replace(/\s+$/,&quot;&quot;)+&quot;,&quot;+ent[i].substring(308,325).replace(/^\s+/,&quot;&quot;).replace(/\s+$/,&quot;&quot;)+&quot;\n&quot;
  }


scriptletResult=salida;
}</script>
                  <type>RHINO</type>
                </scriptlet>
              </scriptletFilter>
              <stripWhitespaceFilter id="d774ee96-fa88-4038-80fe-bde1f73558fd">
                <annotation></annotation>
                <name>Strip Whitespace</name>
              </stripWhitespaceFilter>
              <scriptletFilter id="ddcd038a-20ad-49f4-afb9-b74d2ffcfce0">
                <annotation></annotation>
                <name>Scriptlet</name>
                <scriptlet id="515c472b-f149-4a3f-ad50-93d4ec21067e">
                  <annotation></annotation>
                  <name>default</name>
                  <script>if (scriptletInput !== null) {
  var ent=scriptletInput.split(&quot;\n&quot;);
  var salida=&quot;&quot;;
  //LOCAL
    var lacumvm=0;
    var lcounvm=0;
    var lacumdm=0;
    var lcoundm=0;
    var lacumdevm=0;
    var lcoundevm=0;
    var lacumrdevm=0;
    var lcounrdevm=0;
    var lacumrdvm=0;
    var lcounrdvm=0;
    //USD
    var uacumvm=0;
    var ucounvm=0;
    var uacumdm=0;
    var ucoundm=0;
    var uacumdevm=0;
    var ucoundevm=0;
    var uacumrdevm=0;
    var ucounrdevm=0;
    var uacumrdvm=0;
    var ucounrdvm=0;
	//USDLOCAL
	var ulacumvm=0;  
    var ulacumdm=0;    
    var ulacumdevm=0;   
    var ulacumrdevm=0;  
    var ulacumrdvm=0;
  
  for(i=0;i&lt;ent.length;i++){
  	li=ent[i].split(&quot;,&quot;);
  if(li[2].search(/4\d{15}/g)!=-1){
  	if(li[5]==li[6]){//LOCAL
  	 switch(parseInt(li[4],10)){
  	  	case 1:
  	  		lacumvm= parseFloat(parseFloat(lacumvm) + parseFloat(li[5]/100));
  	  		lcounvm++;
  	  	break;
  	  	case 2:
  			lacumdm= parseFloat(parseFloat(lacumdm) + parseFloat(li[5]/100));
  	  		lcoundm++;
  	  	break;
  	  	case 21:
  			lacumdevm= parseFloat(parseFloat(lacumdevm) + parseFloat(li[5]/100));
  	  		lcoundevm++;
  	  	break;
  	  	case 25:
  			lacumrdvm= parseFloat(parseFloat(lacumrdvm) + parseFloat(li[5]/100));
  	  		lcounrdvm++;
  	  	break;
  	  	case 26:
  			lacumrdevm= parseFloat(parseFloat(lacumrdevm) + parseFloat(li[5]/100));
  	  		lcounrdevm++;
  		
  	  	break;
  	  }
  			
  	}else{//USD
  		switch(parseInt(li[4],10)){
  	  	case 1:
  	  		uacumvm= parseFloat(parseFloat(uacumvm) + parseFloat(li[6]/100));
			ulacumvm= parseFloat(parseFloat(uacumvm) + parseFloat(li[5]/100));
  	  		ucounvm++;
  	  	break;
  	  	case 2:
  			uacumdm= parseFloat(parseFloat(uacumdm) + parseFloat(li[6]/100));
			ulacumdm= parseFloat(parseFloat(uacumdm) + parseFloat(li[5]/100));
  	  		ucoundm++;
  	  	break;
  	  	case 21:
  			uacumdevm= parseFloat(parseFloat(uacumdevm) + parseFloat(li[6]/100));
			ulacumdevm= parseFloat(parseFloat(uacumdevm) + parseFloat(li[5]/100));
  	  		ucoundevm++;
  	  	break;
  	  	case 25:
  			uacumrdvm= parseFloat(parseFloat(uacumrdvm) + parseFloat(li[6]/100));
			ulacumrdvm= parseFloat(parseFloat(uacumrdvm) + parseFloat(li[5]/100));
  	  		ucounrdvm++;
  	  	break;
  	  	case 26:
  			uacumrdevm= parseFloat(parseFloat(uacumrdevm) + parseFloat(li[6]/100));
			ulacumrdevm= parseFloat(parseFloat(uacumrdevm) + parseFloat(li[5]/100));
  	  		ucounrdevm++;
  		
  	  	break;
  	  	}
  		
  	}
  }
  }
  //LOCAL
  salida=&quot;LOCAL\n&quot;
  salida+= &quot;Ventas MC Local(01): &quot;+parseFloat(lacumvm).toFixed(2) + &quot; TX:&quot; +lcounvm ;
  salida+= &quot;\nReversos de Venta MC Local(25): &quot;+parseFloat(lacumrdvm).toFixed(2) + &quot; TX:&quot;+lcounrdvm;
  salida+= &quot;\nDevoluciones MC Local(21): &quot;+parseFloat(lacumdevm).toFixed(2) + &quot; TX:&quot;+lcoundevm;
  salida+= &quot;\nReversos devoluciones MC Local(26): &quot;+parseFloat(lacumrdevm).toFixed(2) + &quot; TX:&quot; +lcounrdevm;
  salida+= &quot;\nDisposiciones MC Local(02): &quot;+parseFloat(lacumdm).toFixed(2) + &quot; TX:&quot;+lcoundm;
  //USD
  salida+=&quot;\n\nUSD\n&quot;
  salida+= &quot;Ventas MC USD(01): &quot;+parseFloat(uacumvm).toFixed(2) + &quot; TX:&quot; +ucounvm +&quot; Ventas USD L:&quot;+parseFloat(ulacumvm).toFixed(2);
  salida+= &quot;\nReversos de Venta MC USD(25): &quot;+parseFloat(uacumrdvm).toFixed(2) + &quot; TX:&quot;+ucounrdvm+&quot; Reverso Ventas USD L:&quot;+parseFloat(ulacumrdvm).toFixed(2);
  salida+= &quot;\nDevoluciones MC USD(21): &quot;+parseFloat(uacumdevm).toFixed(2) + &quot; TX:&quot;+ucoundevm+&quot; Devoluciones USD L:&quot;+parseFloat(ulacumdevm).toFixed(2);
  salida+= &quot;\nReversos devoluciones MC USD(26): &quot;+parseFloat(uacumrdevm).toFixed(2) + &quot; TX:&quot; + ucounrdevm + &quot; Reverso Devoluciones USD L:&quot;+parseFloat(ulacumrdevm).toFixed(2);
  salida+= &quot;\nDisposiciones MC USD(02): &quot;+parseFloat(uacumdm).toFixed(2) + &quot; TX:&quot;+ucoundm + &quot; Disposiciones USD L:&quot;+parseFloat(ulacumdm).toFixed(2);;
  scriptletResult= salida;
  //LOCAL
      scriptletContext.putGlobal(&quot;TX325lacumvv&quot;,lacumvm);
      scriptletContext.putGlobal(&quot;TX325lcounvv&quot;,lcounvm);
      scriptletContext.putGlobal(&quot;TX325lacumdv&quot;,lacumdm);
      scriptletContext.putGlobal(&quot;TX325lcoundv&quot;,lcoundm);
      scriptletContext.putGlobal(&quot;TX325lacumdevv&quot;,lacumdevm);
      scriptletContext.putGlobal(&quot;TX325lcoundevv&quot;,lcoundevm);
      scriptletContext.putGlobal(&quot;TX325lacumrdevv&quot;,lacumrdevm);
      scriptletContext.putGlobal(&quot;TX325lcounrdevv&quot;,lcounrdevm);
      scriptletContext.putGlobal(&quot;TX325lacumrdvv&quot;,lacumrdvm);
      scriptletContext.putGlobal(&quot;TX325lcounrdvv&quot;,lcounrdvm);
      //USD
      scriptletContext.putGlobal(&quot;TX325uacumvv&quot;,uacumvm);
      scriptletContext.putGlobal(&quot;TX325ucounvv&quot;,ucounvm);
      scriptletContext.putGlobal(&quot;TX325uacumdv&quot;,uacumdm);
      scriptletContext.putGlobal(&quot;TX325ucoundv&quot;,ucoundm);
      scriptletContext.putGlobal(&quot;TX325uacumdevv&quot;,uacumdevm);
      scriptletContext.putGlobal(&quot;TX325ucoundevv&quot;,ucoundevm);
      scriptletContext.putGlobal(&quot;TX325uacumrdevv&quot;,uacumrdevm);
      scriptletContext.putGlobal(&quot;TX325ucounrdevv&quot;,ucounrdevm);
      scriptletContext.putGlobal(&quot;TX325uacumrdvv&quot;,uacumrdvm);
      scriptletContext.putGlobal(&quot;TX325ucounrdvv&quot;,ucounrdvm);
	  
	  scriptletContext.putGlobal(&quot;TX325ulacumvv&quot;,ulacumvm);
	  scriptletContext.putGlobal(&quot;TX325ulacumdv&quot;,ulacumdm);
	  scriptletContext.putGlobal(&quot;TX325ulacumdevv&quot;,ulacumdevm);
	  scriptletContext.putGlobal(&quot;TX325ulacumrdevv&quot;,ulacumrdevm);
	  scriptletContext.putGlobal(&quot;TX325ulacumrdvv&quot;,ulacumrdvm);
	  
}</script>
                  <type>RHINO</type>
                </scriptlet>
              </scriptletFilter>
            </filters>
          </expression>
        </flowVariableAssignment>
      </assignments>
      <throttleSize>0</throttleSize>
    </step>
    <returnStep id="4d90906c-a06a-4ec2-b3d0-f17585210166">
      <annotation></annotation>
      <name>Resolved : success</name>
      <bounds>
        <x>457.0</x>
        <y>0.0</y>
      </bounds>
      <layer>-1</layer>
      <hideInbound>false</hideInbound>
      <addResultToRunContext>false</addResultToRunContext>
      <isCriticalStep>false</isCriticalStep>
      <isNonBlocking>false</isNonBlocking>
      <isParallelStep>false</isParallelStep>
      <isSingleResponse>false</isSingleResponse>
      <recordInHistory>false</recordInHistory>
      <recordRawOutput>true</recordRawOutput>
      <recordPrimaryOutput>true</recordPrimaryOutput>
      <checkPointStep>true</checkPointStep>
      <historyCheckPointStep>true</historyCheckPointStep>
      <scriptResultStep>false</scriptResultStep>
      <userPrompt></userPrompt>
      <bindings/>
      <transitions>
        <transition id="bde553da-c5d7-4957-a2e3-770314815c3e">
          <annotation></annotation>
          <name>return</name>
          <command>NEXT</command>
          <linkMode>false</linkMode>
          <responseSymbol>success</responseSymbol>
          <shouldHandoff>false</shouldHandoff>
          <transitionValue>0.0</transitionValue>
          <destination>
            <refId>4d90906c-a06a-4ec2-b3d0-f17585210166</refId>
          </destination>
          <source>
            <refId>4d90906c-a06a-4ec2-b3d0-f17585210166</refId>
          </source>
          <positions/>
        </transition>
      </transitions>
      <properties/>
      <returnStepType>RESOLVED</returnStepType>
      <assignments/>
    </returnStep>
    <step id="400eb22b-2739-45a1-a8ff-3c7722f41ceb">
      <annotation></annotation>
      <name>Get Archivos EMISOR POS Peru</name>
      <bounds>
        <x>0.0</x>
        <y>177.0</y>
      </bounds>
      <layer>-1</layer>
      <hideInbound>false</hideInbound>
      <iconSpec id="1839ceed-dfa1-4487-b5ad-5db8a4e9de5d">
        <baseIcon>flow.png</baseIcon>
        <basePath>System</basePath>
        <readOnly>false</readOnly>
        <layers/>
      </iconSpec>
      <addResultToRunContext>false</addResultToRunContext>
      <isCriticalStep>false</isCriticalStep>
      <isNonBlocking>false</isNonBlocking>
      <isParallelStep>false</isParallelStep>
      <isSingleResponse>false</isSingleResponse>
      <recordInHistory>false</recordInHistory>
      <recordRawOutput>true</recordRawOutput>
      <recordPrimaryOutput>true</recordPrimaryOutput>
      <checkPointStep>true</checkPointStep>
      <historyCheckPointStep>true</historyCheckPointStep>
      <scriptResultStep>false</scriptResultStep>
      <userPrompt></userPrompt>
      <bindings>
        <staticBinding id="7b133bc7-4ef1-4291-9047-7fc56ebaf57a">
          <annotation></annotation>
          <assignFromContext>true</assignFromContext>
          <assignToContext>false</assignToContext>
          <inputType>STRING</inputType>
          <isList>false</isList>
          <required>false</required>
          <isPersisted>true</isPersisted>
          <inputSymbol>Buzon Banco</inputSymbol>
          <listDelimiter>,</listDelimiter>
          <value>MB000088</value>
          <record>false</record>
        </staticBinding>
        <staticBinding id="607d2378-03be-462c-bffa-81a2d1ea2dea">
          <annotation></annotation>
          <assignFromContext>true</assignFromContext>
          <assignToContext>false</assignToContext>
          <inputType>STRING</inputType>
          <isList>false</isList>
          <required>false</required>
          <isPersisted>true</isPersisted>
          <inputSymbol>ArchivoPostBanco</inputSymbol>
          <listDelimiter>,</listDelimiter>
          <value>I2540.B2501TX325</value>
          <record>false</record>
        </staticBinding>
        <staticBinding id="4032fb72-df54-4caa-b05e-34fc80d9aba6">
          <annotation></annotation>
          <fromContextKey>hoy</fromContextKey>
          <assignFromContext>true</assignFromContext>
          <assignToContext>false</assignToContext>
          <inputType>STRING</inputType>
          <isList>false</isList>
          <required>false</required>
          <isPersisted>true</isPersisted>
          <inputSymbol>FechaArchivo</inputSymbol>
          <listDelimiter>,</listDelimiter>
          <value></value>
          <record>false</record>
        </staticBinding>
        <staticBinding id="0325a8a1-d99c-4724-b34d-782acf4d9372">
          <annotation></annotation>
          <assignFromContext>false</assignFromContext>
          <assignToContext>false</assignToContext>
          <inputType>STRING</inputType>
          <isList>false</isList>
          <required>false</required>
          <isPersisted>true</isPersisted>
          <inputSymbol>dosDias</inputSymbol>
          <listDelimiter>,</listDelimiter>
          <value>false</value>
          <record>false</record>
        </staticBinding>
        <staticBinding id="5a6a8d81-eb3c-4f5f-a19e-963e837f714b">
          <annotation></annotation>
          <assignFromContext>false</assignFromContext>
          <assignToContext>false</assignToContext>
          <inputType>STRING</inputType>
          <isList>false</isList>
          <required>false</required>
          <isPersisted>true</isPersisted>
          <inputSymbol>FechaArchivoAntesayer</inputSymbol>
          <listDelimiter>,</listDelimiter>
          <value>170903</value>
          <record>false</record>
        </staticBinding>
      </bindings>
      <transitions>
        <transition id="a060953d-17af-45e2-918a-71361ccb804a">
          <annotation></annotation>
          <name>success</name>
          <command>NEXT</command>
          <linkMode>false</linkMode>
          <responseSymbol>success</responseSymbol>
          <shouldHandoff>false</shouldHandoff>
          <transitionValue>0.0</transitionValue>
          <destination>
            <refId>df326220-390d-4717-807b-ed5e825c49dd</refId>
          </destination>
          <source>
            <refId>400eb22b-2739-45a1-a8ff-3c7722f41ceb</refId>
          </source>
          <positions>
            <point>
              <x>146.0</x>
              <y>209.0</y>
            </point>
            <point>
              <x>139.0</x>
              <y>376.0</y>
            </point>
          </positions>
          <labelPosition>
            <x>333.0</x>
            <y>0.0</y>
          </labelPosition>
        </transition>
      </transitions>
      <properties/>
      <opRef>
        <refId>34da3dd8-2762-4077-a0da-c06de4d353b3</refId>
      </opRef>
      <assignments>
        <flowVariableAssignment id="0c23d5f7-4ce9-4f98-bfa6-f1b231a9e1e8">
          <annotation></annotation>
          <name>assignment</name>
          <action>OVERWRITE</action>
          <assignmentTargetType>FLOW_VARIABLE</assignmentTargetType>
          <contextKey>Archivoincoming</contextKey>
          <expression id="12dc3f06-dd95-4661-973a-8a3799305985">
            <annotation></annotation>
            <name>Result Field: ArchivoIncoming</name>
            <fieldName>ArchivoIncoming</fieldName>
            <sourceType>RAWRESULT</sourceType>
            <filters>
              <replaceAllFilter id="dfaeac4c-9dde-4498-913b-aadc1eebabf5">
                <annotation></annotation>
                <name>Replace</name>
                <ignoreCase>false</ignoreCase>
                <searchString>&apos;</searchString>
                <replaceType>ALL</replaceType>
              </replaceAllFilter>
            </filters>
          </expression>
        </flowVariableAssignment>
        <flowVariableAssignment id="e73e6a12-c7b7-4607-964c-ca89c26b2c2d">
          <annotation></annotation>
          <name>assignment</name>
          <action>OVERWRITE</action>
          <assignmentTargetType>FLOW_VARIABLE</assignmentTargetType>
          <contextKey>ArchivoPOSRE</contextKey>
          <expression id="37b79c37-f674-47ed-8119-e23848c685c5">
            <annotation></annotation>
            <name>Result Field: ArchivoPOSRE</name>
            <fieldName>ArchivoPOSRE</fieldName>
            <sourceType>RAWRESULT</sourceType>
            <filters/>
          </expression>
        </flowVariableAssignment>
      </assignments>
      <throttleSize>0</throttleSize>
    </step>
    <step id="4fedc28d-e325-405a-b332-b0d06f8f8831">
      <annotation></annotation>
      <name>ReadFile SubFlujo [IncomingMI]</name>
      <bounds>
        <x>267.0</x>
        <y>414.0</y>
      </bounds>
      <layer>-1</layer>
      <hideInbound>false</hideInbound>
      <iconSpec id="fcae6e91-1c5f-41eb-b205-b398b96ad11f">
        <baseIcon>flow.png</baseIcon>
        <basePath>System</basePath>
        <readOnly>false</readOnly>
        <layers/>
      </iconSpec>
      <addResultToRunContext>false</addResultToRunContext>
      <isCriticalStep>false</isCriticalStep>
      <isNonBlocking>false</isNonBlocking>
      <isParallelStep>false</isParallelStep>
      <isSingleResponse>false</isSingleResponse>
      <recordInHistory>false</recordInHistory>
      <recordRawOutput>true</recordRawOutput>
      <recordPrimaryOutput>true</recordPrimaryOutput>
      <checkPointStep>true</checkPointStep>
      <historyCheckPointStep>true</historyCheckPointStep>
      <scriptResultStep>false</scriptResultStep>
      <userPrompt></userPrompt>
      <bindings>
        <staticBinding id="bb0f0842-49f2-463c-92c8-1c609b361f14">
          <annotation></annotation>
          <fromContextKey>Archivoincoming</fromContextKey>
          <assignFromContext>true</assignFromContext>
          <assignToContext>false</assignToContext>
          <inputType>STRING</inputType>
          <isList>false</isList>
          <required>false</required>
          <isPersisted>true</isPersisted>
          <inputSymbol>File</inputSymbol>
          <listDelimiter>,</listDelimiter>
          <value></value>
          <record>false</record>
        </staticBinding>
        <staticBinding id="46dc3367-90c5-4d92-b1bc-7d83efe4b64b">
          <annotation></annotation>
          <fromContextKey>BIN</fromContextKey>
          <assignFromContext>true</assignFromContext>
          <assignToContext>false</assignToContext>
          <inputType>STRING</inputType>
          <isList>false</isList>
          <required>false</required>
          <isPersisted>true</isPersisted>
          <inputSymbol>Filter</inputSymbol>
          <listDelimiter>,</listDelimiter>
          <value>10170925H021</value>
          <record>false</record>
        </staticBinding>
      </bindings>
      <transitions>
        <transition id="63ac06ab-a467-4d28-a0a9-f70b6f618b86">
          <annotation></annotation>
          <name>success</name>
          <command>NEXT</command>
          <linkMode>false</linkMode>
          <responseSymbol>success</responseSymbol>
          <shouldHandoff>false</shouldHandoff>
          <transitionValue>0.0</transitionValue>
          <destination>
            <refId>3dc546ff-9723-44bf-b85a-5f3a0ecec7ab</refId>
          </destination>
          <source>
            <refId>4fedc28d-e325-405a-b332-b0d06f8f8831</refId>
          </source>
          <positions>
            <point>
              <x>337.0</x>
              <y>321.0</y>
            </point>
            <point>
              <x>532.0</x>
              <y>194.0</y>
            </point>
          </positions>
          <labelPosition>
            <x>333.0</x>
            <y>0.0</y>
          </labelPosition>
        </transition>
      </transitions>
      <properties/>
      <opRef>
        <refId>4bc1a997-f980-48e6-9979-37d5d93429f0</refId>
      </opRef>
      <assignments>
        <flowVariableAssignment id="01281f11-f49e-4539-a95f-c24bab447b3c">
          <annotation></annotation>
          <name>assignment</name>
          <action>OVERWRITE</action>
          <assignmentTargetType>FLOW_VARIABLE</assignmentTargetType>
          <contextKey>VSS120N</contextKey>
          <expression id="efa928c6-77c3-425a-a4e2-d1e439d8b72a">
            <annotation></annotation>
            <name>Result: Leido</name>
            <fieldName>Leido</fieldName>
            <sourceType>AVAILABLE_RESULT</sourceType>
            <filters>
              <scriptletFilter id="274a2925-ec7e-4a23-8298-37411175bdd3">
                <annotation></annotation>
                <name>Scriptlet</name>
                <scriptlet id="75de240b-7c2d-4f13-bdf8-ac881d1f3aff">
                  <annotation></annotation>
                  <name>default</name>
                  <script>if (scriptletInput !== null) {
  var ent=scriptletInput.split(&quot;\n&quot;);
  var salida=&quot;&quot;;
  ban=false;
  for(i=0;i&lt;ent.length;i++){
  	if ((ban==false)&amp;&amp;(ent[i].search(/REPORT\s+ID\:\s+VSS\-120/g)!=-1)){ban=true;}
  	if ((ban==true)&amp;&amp;(ent[i].search(/END\s+OF\s+VSS\-120\s+REPORT/g)!=-1)){ban=false;}
  	
  	if(ban){
  	salida+=ent[i]+&quot;\n&quot;;
  	}
  }
  scriptletResult=salida;
}</script>
                  <type>RHINO</type>
                </scriptlet>
              </scriptletFilter>
              <stripWhitespaceFilter id="b499a87c-d84d-4d1a-bfad-d177cadad10b">
                <annotation></annotation>
                <name>Strip Whitespace</name>
              </stripWhitespaceFilter>
              <scriptletFilter id="d43d4be1-e8f4-4165-a235-8206a95b983f">
                <annotation></annotation>
                <name>Scriptlet</name>
                <scriptlet id="51429dec-886a-48c4-8804-e4be22baca26">
                  <annotation></annotation>
                  <name>default</name>
                  <script>if (scriptletInput !== null) {
  var ent=scriptletInput.split(&quot;\n&quot;);
  var salida=&quot;&quot;;
  var countvv=0;
  var acumvv=0;
  var countdv=0;
  var acumdv=0;
  var countdevv=0;
  var acumdevv=0;
  var countrevv=0
  var acumrevv=0;
  var countredv=0;
  var acumredv=0;
  
  var ucountvv=0;
    var uacumvv=0;
    var ucountdv=0;
    var uacumdv=0;
    var ucountdevv=0;
    var uacumdevv=0;
    var ucountrevv=0
    var uacumrevv=0;
    var ucountredv=0;
    var uacumredv=0;
    var ban=false;  
  
  for(i=0;i&lt;ent.length;i++){
	if(ent[i].search(/SETTLEMENT\s+CURRENCY\:\s+/g)!=-1){ban=false;}
	if(ent[i].search(/SETTLEMENT\s+CURRENCY\:\s+USD/g)!=-1){ban=true;}
	
	if(!ban){
		if(ent[i].search(/ORIGINAL\s+SALE/g)!=-1){ //ventas
			countvv+=parseInt(ent[i].substring(75,90).replace(/\s+/g,&quot;&quot;).replace(/\,/g,&quot;&quot;));
			acumvv+=parseFloat(ent[i].substring(90,110).replace(/\s+/g,&quot;&quot;).replace(/\,/g,&quot;&quot;));
		}
		if(ent[i].search(/TOTAL\s+MERCHANDISE\s+CREDIT/g)!=-1){//Devoluciones
			countdevv+=parseInt(ent[i].substring(75,90).replace(/\s+/g,&quot;&quot;).replace(/\,/g,&quot;&quot;));
			acumdevv+=parseFloat(ent[i].substring(90,110).replace(/\s+/g,&quot;&quot;).replace(/\,/g,&quot;&quot;));
		}
		if(ent[i].search(/ORIGINAL\s+ADVANCE/g)!=-1){ //Dispo
  	  		countdv+=parseInt(ent[i].substring(75,90).replace(/\s+/g,&quot;&quot;).replace(/\,/g,&quot;&quot;));
  	  		acumdv+=parseFloat(ent[i].substring(90,110).replace(/\s+/g,&quot;&quot;).replace(/\,/g,&quot;&quot;));
  	  	}
		if(ent[i].search(/ORIGINALSALERVRSL/g)!=-1){ //Reverso de venta
  	  	  	countrevv+=parseInt(ent[i].substring(75,90).replace(/\s+/g,&quot;&quot;).replace(/\,/g,&quot;&quot;));
  	  	  	acumrevv+=parseFloat(ent[i].substring(90,110).replace(/\s+/g,&quot;&quot;).replace(/\,/g,&quot;&quot;));
  	  	  	  	}
		if(ent[i].search(/ORIGINALADVANCERVRSL/g)!=-1){ //Reverso dispo
  	  	  	 countredv+=parseInt(ent[i].substring(75,90).replace(/\s+/g,&quot;&quot;).replace(/\,/g,&quot;&quot;));
  	  	  	 acumredv+=parseFloat(ent[i].substring(90,110).replace(/\s+/g,&quot;&quot;).replace(/\,/g,&quot;&quot;));
  	  	  	  	}
	}
	else{
		if(ent[i].search(/ORIGINAL\s+SALE/g)!=-1){ //ventas
  		ucountvv+=parseInt(ent[i].substring(75,90).replace(/\s+/g,&quot;&quot;).replace(/\,/g,&quot;&quot;));
  		uacumvv+=parseFloat(ent[i].substring(90,110).replace(/\s+/g,&quot;&quot;).replace(/\,/g,&quot;&quot;));
		}
		if(ent[i].search(/TOTAL\s+MERCHANDISE\s+CREDIT/g)!=-1){//Devoluciones
  		ucountdevv+=parseInt(ent[i].substring(75,90).replace(/\s+/g,&quot;&quot;).replace(/\,/g,&quot;&quot;));
  		uacumdevv+=parseFloat(ent[i].substring(90,110).replace(/\s+/g,&quot;&quot;).replace(/\,/g,&quot;&quot;));
		}
		if(ent[i].search(/ORIGINAL\s+ADVANCE/g)!=-1){ //Dispo
  	  	ucountdv+=parseInt(ent[i].substring(75,90).replace(/\s+/g,&quot;&quot;).replace(/\,/g,&quot;&quot;));
  	  	uacumdv+=parseFloat(ent[i].substring(90,110).replace(/\s+/g,&quot;&quot;).replace(/\,/g,&quot;&quot;));
  	  	}
		if(ent[i].search(/ORIGINALSALERVRSL/g)!=-1){ //Reverso de venta
  	  	 ucountrevv+=parseInt(ent[i].substring(75,90).replace(/\s+/g,&quot;&quot;).replace(/\,/g,&quot;&quot;));
  	  	 uacumrevv+=parseFloat(ent[i].substring(90,110).replace(/\s+/g,&quot;&quot;).replace(/\,/g,&quot;&quot;));
		}
		if(ent[i].search(/ORIGINALADVANCERVRSL/g)!=-1){ //Reverso dispo
  	  	 ucountredv+=parseInt(ent[i].substring(75,90).replace(/\s+/g,&quot;&quot;).replace(/\,/g,&quot;&quot;));
  	  	 uacumredv+=parseFloat(ent[i].substring(90,110).replace(/\s+/g,&quot;&quot;).replace(/\,/g,&quot;&quot;));
		}
	}
   }
 
  //LOCAL
  salida=&quot;TRX Ventas: &quot;+countvv +&quot;\nAcumulador Ventas: &quot;+acumvv;
  salida+=&quot;\n\nTRX devoluciones: &quot;+countdevv +&quot;\nAcumulador devoluciones: &quot;+acumdevv;
  salida+=&quot;\n\nTRX Dispo: &quot;+countdv +&quot;\nAcumulador Dispo: &quot;+acumdv;
  salida+=&quot;\n\nTRX Reverso de venta: &quot;+countrevv +&quot;\nAcumulador Reversos de Ventas: &quot;+acumrevv;
  salida+=&quot;\n\nTRX Reverso de dispo: &quot;+countredv +&quot;\nAcumulador Reversos de dispo: &quot;+acumredv;
  //USD
  salida+=&quot;\n\nTRX Ventas USD: &quot;+ucountvv +&quot;\nAcumulador Ventas USD: &quot;+uacumvv;
  salida+=&quot;\n\nTRX devoluciones USD: &quot;+ucountdevv +&quot;\nAcumulador devoluciones USD: &quot;+uacumdevv;
  salida+=&quot;\n\nTRX Dispo USD: &quot;+ucountdv +&quot;\nAcumulador Ventas USD: &quot;+uacumdv;
  salida+=&quot;\n\nTRX Reverso de venta USD: &quot;+ucountrevv +&quot;\nAcumulador Reversos de Ventas USD: &quot;+uacumrevv;
  salida+=&quot;\n\nTRX Reverso de dispo USD: &quot;+ucountredv +&quot;\nAcumulador Reversos de dispo USD: &quot;+uacumredv; 
  
  scriptletResult=salida;
  	scriptletContext.putGlobal(&quot;incotxusdventas&quot;,countvv);
    scriptletContext.putGlobal(&quot;incousdventas&quot;,acumvv);
    scriptletContext.putGlobal(&quot;incotxusddispo&quot;,countdv);
    scriptletContext.putGlobal(&quot;incousdispo&quot;,acumdv);
    scriptletContext.putGlobal(&quot;CantidadDevoluciones&quot;,countdevv);
    scriptletContext.putGlobal(&quot;MontoDevoluciones&quot;,acumdevv);
    scriptletContext.putGlobal(&quot;incotxusdventasRV&quot;,countrevv);
    scriptletContext.putGlobal(&quot;incousdventasRV&quot;,acumrevv);
    scriptletContext.putGlobal(&quot;incotxusddispoRV&quot;,countredv);
    scriptletContext.putGlobal(&quot;incousdispoRV&quot;,acumredv);
	
	scriptletContext.putGlobal(&quot;incotxusdventasU&quot;,ucountvv);
    scriptletContext.putGlobal(&quot;incousdventasU&quot;,uacumvv);
    scriptletContext.putGlobal(&quot;incotxusddispoU&quot;,ucountdv);
    scriptletContext.putGlobal(&quot;incousdispoU&quot;,uacumdv);
    scriptletContext.putGlobal(&quot;CantidadDevolucionesU&quot;,ucountdevv);
    scriptletContext.putGlobal(&quot;MontoDevolucionesU&quot;,uacumdevv);
    scriptletContext.putGlobal(&quot;incotxusdventasRVU&quot;,ucountrevv);
    scriptletContext.putGlobal(&quot;incousdventasRVU&quot;,uacumrevv);
    scriptletContext.putGlobal(&quot;incotxusddispoRVU&quot;,ucountredv);
    scriptletContext.putGlobal(&quot;incousdispoRVU&quot;,uacumredv);
    
}</script>
                  <type>RHINO</type>
                </scriptlet>
              </scriptletFilter>
            </filters>
          </expression>
        </flowVariableAssignment>
      </assignments>
      <throttleSize>0</throttleSize>
    </step>
    <step id="3dc546ff-9723-44bf-b85a-5f3a0ecec7ab">
      <annotation>169ea3ad-3558-4166-8dfc-5653f0be2f1c.3dc546ff-9723-44bf-b85a-5f3a0ecec7ab.description</annotation>
      <name>Write to File [POSRE VS Incoming]</name>
      <bounds>
        <x>222.0</x>
        <y>257.0</y>
      </bounds>
      <layer>-1</layer>
      <hideInbound>false</hideInbound>
      <addResultToRunContext>false</addResultToRunContext>
      <isCriticalStep>false</isCriticalStep>
      <isNonBlocking>false</isNonBlocking>
      <isParallelStep>false</isParallelStep>
      <isSingleResponse>true</isSingleResponse>
      <recordInHistory>false</recordInHistory>
      <recordRawOutput>true</recordRawOutput>
      <recordPrimaryOutput>true</recordPrimaryOutput>
      <checkPointStep>true</checkPointStep>
      <historyCheckPointStep>true</historyCheckPointStep>
      <scriptResultStep>false</scriptResultStep>
      <userPrompt></userPrompt>
      <bindings>
        <staticBinding id="827117de-15bf-465d-8c4b-53987371feb9">
          <annotation></annotation>
          <toContextKey></toContextKey>
          <fromContextKey></fromContextKey>
          <assignFromContext>false</assignFromContext>
          <assignToContext>false</assignToContext>
          <inputType>STRING</inputType>
          <isList>false</isList>
          <required>true</required>
          <isPersisted>true</isPersisted>
          <inputSymbol>source</inputSymbol>
          <listDelimiter>,</listDelimiter>
          <value>/aplic/prod/orq/cmi/rpt/sal/RPT-POS-EMI-VISA-${NomBanco}-${FechaAC}.csv</value>
          <record>false</record>
        </staticBinding>
        <staticBinding id="a44b8bea-fb4e-493d-b485-de0890e91e5e">
          <annotation></annotation>
          <toContextKey></toContextKey>
          <fromContextKey></fromContextKey>
          <assignFromContext>false</assignFromContext>
          <assignToContext>false</assignToContext>
          <inputType>STRING</inputType>
          <isList>false</isList>
          <required>true</required>
          <isPersisted>true</isPersisted>
          <inputSymbol>contents</inputSymbol>
          <listDelimiter>,</listDelimiter>
          <value>
,,MERCADOS INTERNACIONALES
,,Banco: ${NomBanco}				
,,Operacion Emisor VISA - POS					

,,REPORTE DE CONCILIACION DE CIFRAS,,Fecha Liquidacion,${FechaAC}
,,Liquidacion VISA VS Archivo POSRE06					

,,CONCILIACION INCOMING

,,INCOMING VISA,,,,,ArchivoPOSRE06
,Concepto,Operacon Internacional,,,Operacion Local,,Operacion Internacional,,,Operacion Local,,Diferencia
,Concepto,TXs,Importe Dolares,Moneda Local,TXs,Importe Moneda Local,TXs,Importe Dolares,Importe Mondea Local,TXs,Importe Moneda Local,TXs,Importe Mondea Local,,,Calcular Tasa
,Ventas,${incotxusdventasU},${incousdventasU},=D14*D22,${incotxusdventas},${incousdventas},${TX325ucounvv},${TX325uacumvv},${TX325ulacumvv},${TX325lcounvv},${TX325lacumvv},=ABS(C14+F14-H14-K14),=ABS(E14+G14-J14-L14),,,=ABS(G14-J14-L14),
,Reverso,${incotxusdventasRVU},-${incousdventasRVU},=D15*D22,${incotxusdventasRV},-${incousdventasRV},${TX325ucounrdvv},${TX325uacumrdvv},${TX325ulacumrdvv},${TX325lcounrdvv},${TX325lacumrdvv},=ABS(C15+F15-H15-K15),=ABS(E15+G15-J15-L15)
,Devoluciones,${CantidadDevolucionesU},-${MontoDevolucionesU},=D16*D22,${CantidadDevoluciones},-${MontoDevoluciones},${TX325ucoundevv},${TX325uacumdevv},${TX325ulacumdevv},${TX325lcoundevv},-${TX325lacumdevv},=ABS(C16+F16-H16-K16),=ABS(E16+G16-J16-L16)
,Reverso,${incotxusddispoRVU},${incousdispoRVU},=D17*D22,${incotxusddispoRV},${incousdispoRV},${TX325ucounrdevv},${TX325uacumrdevv},${TX325ulacumrdevv},${TX325lcounrdevv},${TX325lacumrdvv},=ABS(C17+F17-H17-K17),=ABS(E17+G17-J17-L17)
,Disposiciones,${incotxusddispoU},${incousdispoU},=D18*D22,${incotxusddispo},${incousdispo},${TX325ucoundv},${TX325uacumdv},${TX325ulacumdv},${TX325lcoundv},${TX325lacumdv},=ABS(C18+F18-H18-K18),=ABS(E18+G18-J18-L18)
,Totales,=SUM(C14:C18),=SUM(D14:D18),=SUM(E14:E18),=SUM(F14:F18),=SUM(G14:G18),=SUM(H14:H18),=SUM(I14:I18),=SUM(J14:J18),=SUM(K14:K18),=SUM(L14:L18),=SUM(M14:M18),=SUM(N14:N18)


,,Tasa de cambio,=Q14/D14,</value>
          <record>false</record>
        </staticBinding>
        <staticBinding id="6c2a376a-5cda-44bd-bde3-e8a8e5170f19">
          <annotation></annotation>
          <assignFromContext>false</assignFromContext>
          <assignToContext>false</assignToContext>
          <inputType>STRING</inputType>
          <isList>false</isList>
          <required>false</required>
          <isPersisted>true</isPersisted>
          <inputSymbol>delimiter</inputSymbol>
          <listDelimiter>,</listDelimiter>
          <record>false</record>
        </staticBinding>
        <staticBinding id="973c525e-09e1-4c2d-96da-909df3811a3a">
          <annotation></annotation>
          <assignFromContext>false</assignFromContext>
          <assignToContext>false</assignToContext>
          <inputType>STRING</inputType>
          <isList>false</isList>
          <required>false</required>
          <isPersisted>true</isPersisted>
          <inputSymbol>overwrite</inputSymbol>
          <listDelimiter>,</listDelimiter>
          <value>true</value>
          <record>false</record>
        </staticBinding>
      </bindings>
      <transitions>
        <transition id="482d2ced-d014-4fbb-8ac1-19e55bdc0496">
          <annotation></annotation>
          <name>done</name>
          <command>NEXT</command>
          <linkMode>false</linkMode>
          <responseSymbol>done</responseSymbol>
          <shouldHandoff>false</shouldHandoff>
          <transitionValue>0.0</transitionValue>
          <destination>
            <refId>6039fad4-4f9d-4fbd-a167-de2e2c3bdb13</refId>
          </destination>
          <source>
            <refId>3dc546ff-9723-44bf-b85a-5f3a0ecec7ab</refId>
          </source>
          <positions>
            <point>
              <x>319.0</x>
              <y>257.0</y>
            </point>
            <point>
              <x>368.0</x>
              <y>111.0</y>
            </point>
          </positions>
          <labelPosition>
            <x>333.0</x>
            <y>0.0</y>
          </labelPosition>
        </transition>
      </transitions>
      <properties/>
      <opRef>
        <refId>af728dc4-d7a0-4e8e-917a-74c188f2e470</refId>
      </opRef>
      <assignments/>
      <throttleSize>0</throttleSize>
    </step>
    <step id="6039fad4-4f9d-4fbd-a167-de2e2c3bdb13">
      <annotation>169ea3ad-3558-4166-8dfc-5653f0be2f1c.6039fad4-4f9d-4fbd-a167-de2e2c3bdb13.description</annotation>
      <name>SFTP Put</name>
      <bounds>
        <x>276.0</x>
        <y>94.0</y>
      </bounds>
      <layer>-1</layer>
      <hideInbound>false</hideInbound>
      <iconSpec id="c6aaf288-c126-427b-a1d5-94a15a0493f1">
        <baseIcon>document_text.png</baseIcon>
        <basePath>/Operating System/</basePath>
        <readOnly>false</readOnly>
        <layers>
          <iconSpec id="af317303-e605-4ec0-8451-9f880ecf1da0">
            <baseIcon>send.png</baseIcon>
            <basePath>/Annotations/</basePath>
            <readOnly>false</readOnly>
            <layers/>
          </iconSpec>
        </layers>
      </iconSpec>
      <addResultToRunContext>false</addResultToRunContext>
      <isCriticalStep>false</isCriticalStep>
      <isNonBlocking>false</isNonBlocking>
      <isParallelStep>false</isParallelStep>
      <isSingleResponse>true</isSingleResponse>
      <recordInHistory>false</recordInHistory>
      <recordRawOutput>true</recordRawOutput>
      <recordPrimaryOutput>true</recordPrimaryOutput>
      <checkPointStep>true</checkPointStep>
      <historyCheckPointStep>true</historyCheckPointStep>
      <scriptResultStep>false</scriptResultStep>
      <userPrompt></userPrompt>
      <bindings>
        <staticBinding id="98fdae5b-4628-4e4d-8c34-80f7a5737a58">
          <annotation></annotation>
          <fromContextKey>IP SFTP DominioD SalidaRPT</fromContextKey>
          <assignFromContext>true</assignFromContext>
          <assignToContext>false</assignToContext>
          <inputType>STRING</inputType>
          <isList>false</isList>
          <required>true</required>
          <isPersisted>true</isPersisted>
          <inputSymbol>host</inputSymbol>
          <listDelimiter>,</listDelimiter>
          <value></value>
          <record>false</record>
        </staticBinding>
        <staticBinding id="ecdf2907-af04-477a-a08b-92edece74797">
          <annotation></annotation>
          <toContextKey></toContextKey>
          <fromContextKey></fromContextKey>
          <assignFromContext>false</assignFromContext>
          <assignToContext>false</assignToContext>
          <inputType>STRING</inputType>
          <isList>false</isList>
          <required>false</required>
          <isPersisted>true</isPersisted>
          <inputSymbol>port</inputSymbol>
          <listDelimiter>,</listDelimiter>
          <value>22</value>
          <record>false</record>
        </staticBinding>
        <identityBinding id="8324f3c5-e1c3-4bc5-bf8e-0de7a5387cdc">
          <annotation></annotation>
          <assignFromContext>false</assignFromContext>
          <assignToContext>false</assignToContext>
          <inputType>STRING</inputType>
          <isList>false</isList>
          <required>true</required>
          <isPersisted>true</isPersisted>
          <inputSymbol>username</inputSymbol>
          <listDelimiter>,</listDelimiter>
          <record>false</record>
          <link>
            <refId>d4c6325e-a7ad-4d27-aa51-07a4ad171d79</refId>
            <refName>SFTP DominioD SalidaRPT</refName>
          </link>
          <identityAttribute>USERNAME</identityAttribute>
        </identityBinding>
        <identityBinding id="2f875b30-990e-4575-9445-e9e44d474d93">
          <annotation></annotation>
          <assignFromContext>false</assignFromContext>
          <assignToContext>false</assignToContext>
          <inputType>ENCRYPTED</inputType>
          <isList>false</isList>
          <required>true</required>
          <isPersisted>true</isPersisted>
          <inputSymbol>password</inputSymbol>
          <listDelimiter>,</listDelimiter>
          <record>false</record>
          <link>
            <refId>d4c6325e-a7ad-4d27-aa51-07a4ad171d79</refId>
            <refName>SFTP DominioD SalidaRPT</refName>
          </link>
          <identityAttribute>PASSWORD</identityAttribute>
        </identityBinding>
        <staticBinding id="a9a3cf47-6bc7-4c8e-a2db-0840194daa9f">
          <annotation></annotation>
          <assignFromContext>false</assignFromContext>
          <assignToContext>false</assignToContext>
          <inputType>STRING</inputType>
          <isList>false</isList>
          <required>true</required>
          <isPersisted>true</isPersisted>
          <inputSymbol>localFile</inputSymbol>
          <listDelimiter>,</listDelimiter>
          <value>/aplic/prod/orq/cmi/rpt/sal/RPT-POS-EMI-VISA-${NomBanco}-${FechaAC}.csv</value>
          <record>false</record>
        </staticBinding>
        <staticBinding id="5b130c18-9c07-45af-a9ff-9c78c0b784dd">
          <annotation></annotation>
          <assignFromContext>false</assignFromContext>
          <assignToContext>false</assignToContext>
          <inputType>STRING</inputType>
          <isList>false</isList>
          <required>true</required>
          <isPersisted>true</isPersisted>
          <inputSymbol>remoteLocation</inputSymbol>
          <listDelimiter>,</listDelimiter>
          <value>/aplic/prod/orq/cmi/rpt/</value>
          <record>false</record>
        </staticBinding>
        <staticBinding id="f4e97811-f5c1-402e-a61a-f4eed28c46e0">
          <annotation></annotation>
          <assignFromContext>false</assignFromContext>
          <assignToContext>false</assignToContext>
          <inputType>STRING</inputType>
          <isList>false</isList>
          <required>false</required>
          <isPersisted>true</isPersisted>
          <inputSymbol>closeSession</inputSymbol>
          <listDelimiter>,</listDelimiter>
          <value>true</value>
          <record>false</record>
        </staticBinding>
      </bindings>
      <transitions>
        <transition id="0c7e947a-4d33-43ee-8ad6-d6c35941e331">
          <annotation></annotation>
          <name>done</name>
          <command>NEXT</command>
          <linkMode>false</linkMode>
          <responseSymbol>done</responseSymbol>
          <shouldHandoff>false</shouldHandoff>
          <transitionValue>0.0</transitionValue>
          <destination>
            <refId>4d90906c-a06a-4ec2-b3d0-f17585210166</refId>
          </destination>
          <source>
            <refId>6039fad4-4f9d-4fbd-a167-de2e2c3bdb13</refId>
          </source>
          <positions>
            <point>
              <x>368.0</x>
              <y>111.0</y>
            </point>
            <point>
              <x>758.0</x>
              <y>61.0</y>
            </point>
          </positions>
          <labelPosition>
            <x>333.0</x>
            <y>0.0</y>
          </labelPosition>
        </transition>
      </transitions>
      <properties/>
      <opRef>
        <refId>d0281620-067b-46b8-8053-965857395cdc</refId>
      </opRef>
      <assignments/>
      <throttleSize>0</throttleSize>
    </step>
  </steps>
  <startSteps>597b944e-813f-4868-9355-22499d5cc024</startSteps>
</flow>