<?xml version="1.0" encoding="UTF-8"?>
<flow id="8769aa7f-4026-4683-bfe6-0773be224256">
  <descriptionCdata><![CDATA[]]></descriptionCdata>
  <annotation></annotation>
  <name>Cociliaciones Miselaneos</name>
  <categories/>
  <inputs>
    <staticBinding id="7cc8490b-3a95-44c4-89cc-70ed005e0b20">
      <annotation></annotation>
      <assignFromContext>true</assignFromContext>
      <assignToContext>false</assignToContext>
      <inputType>STRING</inputType>
      <isList>false</isList>
      <required>false</required>
      <isPersisted>true</isPersisted>
      <inputSymbol>FechaEp7</inputSymbol>
      <listDelimiter>,</listDelimiter>
      <value>171012</value>
      <record>false</record>
    </staticBinding>
  </inputs>
  <possibleResponses>
    <opResponse id="4bd4db96-f122-4b9b-bff6-0b318649c6cc">
      <annotation></annotation>
      <name>success</name>
      <isDefault>true</isDefault>
      <onFailure>false</onFailure>
      <type>RESOLVED</type>
      <matchRules/>
    </opResponse>
    <opResponse id="6b547c29-aee1-414e-9a05-94675fde9c9c">
      <annotation></annotation>
      <name>failure</name>
      <isDefault>false</isDefault>
      <onFailure>true</onFailure>
      <type>ERROR</type>
      <matchRules/>
    </opResponse>
  </possibleResponses>
  <availableResultExpressions/>
  <resultExpression id="49b3d0b4-3c21-4962-a1c4-fbd395929ebc">
    <annotation></annotation>
    <name>FailureMessage</name>
    <fieldName>FailureMessage</fieldName>
    <sourceType>RAWRESULT</sourceType>
    <filters/>
  </resultExpression>
  <iconSpec id="8f1577e9-8ad8-4159-86eb-f4ff60b9c21d">
    <baseIcon>flow.png</baseIcon>
    <basePath>System</basePath>
    <readOnly>false</readOnly>
    <layers/>
  </iconSpec>
  <callouts/>
  <checkPointFlow>true</checkPointFlow>
  <compatibleRuntimeContext>false</compatibleRuntimeContext>
  <historyCheckPointFlow>true</historyCheckPointFlow>
  <steps>
    <step id="bb5af531-4417-493c-a91b-a3b683209b3a">
      <annotation></annotation>
      <name>Obtener EP7_31</name>
      <bounds>
        <x>0.0</x>
        <y>0.0</y>
      </bounds>
      <layer>-1</layer>
      <hideInbound>false</hideInbound>
      <addResultToRunContext>false</addResultToRunContext>
      <isCriticalStep>false</isCriticalStep>
      <isNonBlocking>false</isNonBlocking>
      <isParallelStep>false</isParallelStep>
      <isSingleResponse>false</isSingleResponse>
      <recordInHistory>false</recordInHistory>
      <recordRawOutput>true</recordRawOutput>
      <recordPrimaryOutput>true</recordPrimaryOutput>
      <checkPointStep>true</checkPointStep>
      <historyCheckPointStep>true</historyCheckPointStep>
      <scriptResultStep>false</scriptResultStep>
      <userPrompt></userPrompt>
      <bindings>
        <staticBinding id="c2fabd5d-5e19-456a-a1e3-553d355d4d7a">
          <annotation></annotation>
          <assignFromContext>true</assignFromContext>
          <assignToContext>false</assignToContext>
          <inputType>STRING</inputType>
          <isList>false</isList>
          <required>false</required>
          <isPersisted>true</isPersisted>
          <inputSymbol>FechaEp7</inputSymbol>
          <listDelimiter>,</listDelimiter>
          <value>171012</value>
          <record>false</record>
        </staticBinding>
      </bindings>
      <transitions>
        <transition id="e6a29105-d118-43c9-b1ac-4b5cb1f3084e">
          <annotation></annotation>
          <name>failure</name>
          <command>NEXT</command>
          <linkMode>false</linkMode>
          <responseSymbol>failure</responseSymbol>
          <shouldHandoff>false</shouldHandoff>
          <transitionValue>0.0</transitionValue>
          <destination>
            <refId>e6493f0b-3be4-46df-a299-964bfd9059aa</refId>
          </destination>
          <source>
            <refId>bb5af531-4417-493c-a91b-a3b683209b3a</refId>
          </source>
          <positions>
            <point>
              <x>97.0</x>
              <y>34.0</y>
            </point>
            <point>
              <x>251.0</x>
              <y>34.0</y>
            </point>
          </positions>
          <labelPosition>
            <x>333.0</x>
            <y>0.0</y>
          </labelPosition>
        </transition>
        <transition id="731ed1fe-908b-4fd8-99c9-a4e2aeb10baa">
          <annotation></annotation>
          <name>success</name>
          <command>NEXT</command>
          <linkMode>false</linkMode>
          <responseSymbol>success</responseSymbol>
          <shouldHandoff>false</shouldHandoff>
          <transitionValue>0.0</transitionValue>
          <destination>
            <refId>260dd1fd-8f71-43df-83c9-eb1d009c43b1</refId>
          </destination>
          <source>
            <refId>bb5af531-4417-493c-a91b-a3b683209b3a</refId>
          </source>
          <positions>
            <point>
              <x>50.0</x>
              <y>34.0</y>
            </point>
            <point>
              <x>161.0</x>
              <y>154.0</y>
            </point>
          </positions>
          <labelPosition>
            <x>333.0</x>
            <y>0.0</y>
          </labelPosition>
        </transition>
      </transitions>
      <properties/>
      <opRef>
        <refId>fee3dc89-4200-42d3-a399-668017ace574</refId>
      </opRef>
      <assignments>
        <flowVariableAssignment id="ebb05f75-1316-4003-96c8-b91e1232609a">
          <annotation></annotation>
          <name>assignment</name>
          <action>OVERWRITE</action>
          <assignmentTargetType>FLOW_VARIABLE</assignmentTargetType>
          <contextKey>archivoEP7</contextKey>
          <expression id="7554f664-be10-48c7-942f-60191254506e">
            <annotation></annotation>
            <name>Result Field: archivoEP7</name>
            <fieldName>archivoEP7</fieldName>
            <sourceType>RAWRESULT</sourceType>
            <filters/>
          </expression>
        </flowVariableAssignment>
      </assignments>
      <throttleSize>0</throttleSize>
    </step>
    <returnStep id="e9d948c4-9627-429b-9d7c-d52f3c9339b5">
      <annotation></annotation>
      <name>Resolved : success</name>
      <bounds>
        <x>246.0</x>
        <y>0.0</y>
      </bounds>
      <layer>-1</layer>
      <hideInbound>false</hideInbound>
      <addResultToRunContext>false</addResultToRunContext>
      <isCriticalStep>false</isCriticalStep>
      <isNonBlocking>false</isNonBlocking>
      <isParallelStep>false</isParallelStep>
      <isSingleResponse>false</isSingleResponse>
      <recordInHistory>false</recordInHistory>
      <recordRawOutput>true</recordRawOutput>
      <recordPrimaryOutput>true</recordPrimaryOutput>
      <checkPointStep>true</checkPointStep>
      <historyCheckPointStep>true</historyCheckPointStep>
      <scriptResultStep>false</scriptResultStep>
      <userPrompt></userPrompt>
      <bindings/>
      <transitions>
        <transition id="77a6da41-aeac-417e-a451-ef371ffbb29b">
          <annotation></annotation>
          <name>return</name>
          <command>NEXT</command>
          <linkMode>false</linkMode>
          <responseSymbol>success</responseSymbol>
          <shouldHandoff>false</shouldHandoff>
          <transitionValue>0.0</transitionValue>
          <destination>
            <refId>e9d948c4-9627-429b-9d7c-d52f3c9339b5</refId>
          </destination>
          <source>
            <refId>e9d948c4-9627-429b-9d7c-d52f3c9339b5</refId>
          </source>
          <positions/>
        </transition>
      </transitions>
      <properties/>
      <returnStepType>RESOLVED</returnStepType>
      <assignments/>
    </returnStep>
    <returnStep id="e6493f0b-3be4-46df-a299-964bfd9059aa">
      <annotation></annotation>
      <name>Error : failure</name>
      <bounds>
        <x>0.0</x>
        <y>189.0</y>
      </bounds>
      <layer>-1</layer>
      <hideInbound>false</hideInbound>
      <addResultToRunContext>false</addResultToRunContext>
      <isCriticalStep>false</isCriticalStep>
      <isNonBlocking>false</isNonBlocking>
      <isParallelStep>false</isParallelStep>
      <isSingleResponse>false</isSingleResponse>
      <recordInHistory>false</recordInHistory>
      <recordRawOutput>true</recordRawOutput>
      <recordPrimaryOutput>true</recordPrimaryOutput>
      <checkPointStep>true</checkPointStep>
      <historyCheckPointStep>true</historyCheckPointStep>
      <scriptResultStep>false</scriptResultStep>
      <userPrompt></userPrompt>
      <bindings/>
      <transitions>
        <transition id="990c4fa4-198c-46b2-b9ba-795df12aefcb">
          <annotation></annotation>
          <name>return</name>
          <command>NEXT</command>
          <linkMode>false</linkMode>
          <responseSymbol>failure</responseSymbol>
          <shouldHandoff>false</shouldHandoff>
          <transitionValue>0.0</transitionValue>
          <destination>
            <refId>e6493f0b-3be4-46df-a299-964bfd9059aa</refId>
          </destination>
          <source>
            <refId>e6493f0b-3be4-46df-a299-964bfd9059aa</refId>
          </source>
          <positions/>
        </transition>
      </transitions>
      <properties/>
      <returnStepType>ERROR</returnStepType>
      <assignments/>
    </returnStep>
    <step id="260dd1fd-8f71-43df-83c9-eb1d009c43b1">
      <annotation></annotation>
      <name>ReadFile SubFlujo DAT Files</name>
      <bounds>
        <x>115.0</x>
        <y>2.0</y>
      </bounds>
      <layer>-1</layer>
      <hideInbound>false</hideInbound>
      <addResultToRunContext>false</addResultToRunContext>
      <isCriticalStep>false</isCriticalStep>
      <isNonBlocking>false</isNonBlocking>
      <isParallelStep>false</isParallelStep>
      <isSingleResponse>false</isSingleResponse>
      <recordInHistory>false</recordInHistory>
      <recordRawOutput>true</recordRawOutput>
      <recordPrimaryOutput>true</recordPrimaryOutput>
      <checkPointStep>true</checkPointStep>
      <historyCheckPointStep>true</historyCheckPointStep>
      <scriptResultStep>false</scriptResultStep>
      <userPrompt></userPrompt>
      <bindings>
        <staticBinding id="75c79fed-97ff-424c-a05b-c3c2fc7ec5d2">
          <annotation></annotation>
          <fromContextKey>archivoEP7</fromContextKey>
          <assignFromContext>true</assignFromContext>
          <assignToContext>false</assignToContext>
          <inputType>STRING</inputType>
          <isList>false</isList>
          <required>false</required>
          <isPersisted>true</isPersisted>
          <inputSymbol>File</inputSymbol>
          <listDelimiter>,</listDelimiter>
          <value></value>
          <record>false</record>
        </staticBinding>
        <staticBinding id="15d8e945-cc08-42f5-b2b0-0516f7cf6f08">
          <annotation></annotation>
          <assignFromContext>false</assignFromContext>
          <assignToContext>false</assignToContext>
          <inputType>STRING</inputType>
          <isList>false</isList>
          <required>false</required>
          <isPersisted>true</isPersisted>
          <inputSymbol>Filter</inputSymbol>
          <listDelimiter>,</listDelimiter>
          <value></value>
          <record>false</record>
        </staticBinding>
      </bindings>
      <transitions>
        <transition id="51ebec13-0d94-4040-a7bc-d7e66e76564c">
          <annotation></annotation>
          <name>success</name>
          <command>NEXT</command>
          <linkMode>false</linkMode>
          <responseSymbol>success</responseSymbol>
          <shouldHandoff>false</shouldHandoff>
          <transitionValue>0.0</transitionValue>
          <destination>
            <refId>e9d948c4-9627-429b-9d7c-d52f3c9339b5</refId>
          </destination>
          <source>
            <refId>260dd1fd-8f71-43df-83c9-eb1d009c43b1</refId>
          </source>
          <positions>
            <point>
              <x>161.0</x>
              <y>154.0</y>
            </point>
            <point>
              <x>296.0</x>
              <y>34.0</y>
            </point>
          </positions>
          <labelPosition>
            <x>333.0</x>
            <y>0.0</y>
          </labelPosition>
        </transition>
      </transitions>
      <properties/>
      <opRef>
        <refId>c5605579-be66-4f68-a2af-b8e4771ac9f6</refId>
      </opRef>
      <assignments/>
      <throttleSize>0</throttleSize>
    </step>
  </steps>
  <startSteps>bb5af531-4417-493c-a91b-a3b683209b3a</startSteps>
</flow>